coss/__init__.py
coss/interpolation.py
coss/utils.py
coss/areal/__init__.py
coss/areal/areal_geobootstrap.py
coss/areal/areal_weighting.py
coss/areal/dasy.py
coss/areal/model.py
coss-0.12.4.dist-info/LICENSE
coss-0.12.4.dist-info/METADATA
coss-0.12.4.dist-info/WHEEL
coss-0.12.4.dist-info/top_level.txt
coss-0.12.4.dist-info/RECORD
