Metadata-Version: 2.1
Name: coss
Version: 0.12.4
Summary: Python tools for spatial interpolation
Home-page: https://github.com/tastatham/coss
Author: Thomas Statham
Author-email: tastatham@gmail.com
License: MIT
Keywords: spatial,interpolation,support,areal
License-File: LICENSE
Requires-Dist: statsmodels (==0.13.1)
Requires-Dist: geopandas (==0.10.2)
Requires-Dist: geobootstrap (==0.12)
Requires-Dist: dask-geopandas (==0.2.0)
Requires-Dist: tobler (==0.8.2)
Requires-Dist: astropy
